jyhelper/__init__.py
jyhelper/common.py
jyhelper/db.py
jyhelper/dictHelper.py
jyhelper/docHelper.py
jyhelper/feishuRobot.py
jyhelper/file.py
jyhelper/fileHelper.py
jyhelper/listHelper.py
jyhelper/mongo.py
jyhelper/mysql.py
jyhelper/strHelper.py
jyhelper/sysHelper.py
jyhelper/timeHelper.py
jyhelper-25.12.25.3.dist-info/METADATA
jyhelper-25.12.25.3.dist-info/WHEEL
jyhelper-25.12.25.3.dist-info/top_level.txt
jyhelper-25.12.25.3.dist-info/RECORD
