Metadata-Version: 2.1
Name: jyhelper
Version: 25.12.25.3
Summary: 各种实用、常用的小函数、类
Home-page: https://pypi.org/project/jyhelper/
Author: JY
Author-email: your-email@example.com
License: UNKNOWN
Platform: UNKNOWN
Requires-Python: >=3.5
Requires-Dist: pymysql
Requires-Dist: requests
Requires-Dist: sqlparse
Requires-Dist: pymongo
